deepepochs/__init__.py
deepepochs/loops.py
deepepochs/metrics.py
deepepochs/optimizer.py
deepepochs/patches.py
deepepochs/tools.py
deepepochs/callbacks/__init__.py
deepepochs/callbacks/analyze.py
deepepochs/callbacks/callback.py
deepepochs/callbacks/check.py
deepepochs/callbacks/default.py
deepepochs/callbacks/grad_clip.py
deepepochs/callbacks/interprete.py
deepepochs/callbacks/log.py
deepepochs/callbacks/lr_find.py
deepepochs/trainer/__init__.py
deepepochs/trainer/epoch_task.py
deepepochs/trainer/loss_wrapper.py
deepepochs/trainer/model_wrapper.py
deepepochs/trainer/trainer.py
deepepochs-0.6.14.dist-info/LICENSE
deepepochs-0.6.14.dist-info/METADATA
deepepochs-0.6.14.dist-info/WHEEL
deepepochs-0.6.14.dist-info/top_level.txt
deepepochs-0.6.14.dist-info/RECORD
