Metadata-Version: 2.1
Name: deepepochs
Version: 0.6.14
Summary: An easy-to-use tool for training Pytorch deep learning models
Home-page: https://github.com/hitlic/deepepochs
Author: hitlic
Author-email: liuchen.lic@gmail.com
License: MIT
Classifier: Development Status :: 3 - Alpha
Classifier: Programming Language :: Python :: 3
Classifier: License :: OSI Approved :: MIT License
Classifier: Operating System :: OS Independent
Requires-Python: >=3.8
License-File: LICENSE
Requires-Dist: torch >=2.0.0
Requires-Dist: pyyaml >=5.4
Requires-Dist: tqdm >=4.62
Requires-Dist: numpy >1.21
Requires-Dist: matplotlib >=3.6
Requires-Dist: tensorboard >=2.12
Requires-Dist: scikit-learn >=0.22
Requires-Dist: pandas >=1.3
Requires-Dist: accelerate >=0.24
